sudachi_sentence_splitter-0.1.0.dist-info/METADATA
sudachi_sentence_splitter-0.1.0.dist-info/WHEEL
sudachi_sentence_splitter/__init__.py
sudachi_sentence_splitter/sudachi_sentence_splitter.cpython-311-darwin.so
sudachi_sentence_splitter-0.1.0.dist-info/RECORD
